ytam/__init__.py
ytam/cmd.py
ytam/discogs.py
ytam/error.py
ytam/font.py
ytam/title.py
ytam/version.py
ytam/ytam.py
ytam/check/__init__.py
ytam/check/check.jpg
ytam/check/check.txt
ytam/metadata/__init__.py
ytam-0.4.5.dist-info/LICENSE
ytam-0.4.5.dist-info/METADATA
ytam-0.4.5.dist-info/WHEEL
ytam-0.4.5.dist-info/entry_points.txt
ytam-0.4.5.dist-info/top_level.txt
ytam-0.4.5.dist-info/RECORD
