Metadata-Version: 2.1
Name: ytam
Version: 0.4.5
Summary: A commandline utility that enables the creation of albums from Youtube playlists.
Home-page: https://github.com/jayathungek/ytam
Author: jayathungek
Author-email: jayathunge.work@gmail.com
License: UNKNOWN
Platform: UNKNOWN
Classifier: Programming Language :: Python :: 3
Classifier: License :: OSI Approved :: MIT License
Classifier: Operating System :: OS Independent
Requires-Python: >=3.6
License-File: LICENSE
Requires-Dist: certifi
Requires-Dist: pytube
Requires-Dist: chardet
Requires-Dist: colorama
Requires-Dist: idna
Requires-Dist: mutagen
Requires-Dist: requests
Requires-Dist: urllib3
Requires-Dist: python-ffmpeg
